flutter_logo_updater/__init__.py
flutter_logo_updater/__main__.py
flutter_logo_updater/android_finder.py
flutter_logo_updater/ios_finder.py
flutter_logo_updater/mapping.json
flutter_logo_updater-0.0.4.dist-info/METADATA
flutter_logo_updater-0.0.4.dist-info/WHEEL
flutter_logo_updater-0.0.4.dist-info/entry_points.txt
flutter_logo_updater-0.0.4.dist-info/top_level.txt
flutter_logo_updater-0.0.4.dist-info/RECORD
