Metadata-Version: 2.1
Name: flutter-logo-updater
Version: 0.0.4
Summary: Tool to update all app icons in flutter project
Home-page: https://github.com/caojianfeng/flutter_logo_updater
Author: JeffreyCao
Author-email: jeffreycao1024@gmail.com
License: MIT Licence
Keywords: pip,flutter_logo_updater
Platform: any
Classifier: Programming Language :: Python :: 3
Classifier: License :: OSI Approved :: MIT License
Classifier: Operating System :: OS Independent
Requires-Python: >=3.6
Requires-Dist: Pillow
Requires-Dist: ezutils
